README.md
setup.py
shoutout.py
shoutout.egg-info/PKG-INFO
shoutout.egg-info/SOURCES.txt
shoutout.egg-info/dependency_links.txt
shoutout.egg-info/top_level.txt