Metadata-Version: 1.1
Name: shoutout
Version: 0.0.2
Summary: Shout out loud
Home-page: https://github.com/hongkunyoo/shoutout
Author: Hongkun Yoo
Author-email: hongkunyoo@gmail.com
License: MIT
Download-URL: https://github.com/hongkunyoo/shoutout
Keywords: Large letters,large letter printer,Shout out loud
Platform: UNKNOWN
